src/__init__.py
src/__main__.py
src/functions.py
ASCIIcli-0.1.1.dist-info/LICENSE
ASCIIcli-0.1.1.dist-info/METADATA
ASCIIcli-0.1.1.dist-info/WHEEL
ASCIIcli-0.1.1.dist-info/entry_points.txt
ASCIIcli-0.1.1.dist-info/top_level.txt
ASCIIcli-0.1.1.dist-info/RECORD
