Metadata-Version: 2.1
Name: ASCIIcli
Version: 0.1.1
Summary: A command-line tool that converts images to ASCII art.
Home-page: https://github.com/mrq-andras/asciicli
Author: mrq-andras
License: MIT
Classifier: Programming Language :: Python :: 3
Classifier: Programming Language :: Python :: 3.9
Classifier: License :: OSI Approved :: MIT License
Classifier: Operating System :: OS Independent
Requires-Python: >=3.6
License-File: LICENSE
Requires-Dist: Pillow
